[
  {
    "name": "11-mage-na-ii-pidar-hassan-baba-320",
    "originalName": "11 - Mage Na II - Pidar  Hassan Baba (320).mp3",
    "path": "uploads/11-mage-na-ii-pidar-hassan-baba-320.enc",
    "timestamp": 1777495495354,
    "expire_in_hours": 1,
    "passwordProtected": false
  },
  {
    "name": "113-mese-man-nashod-behzad-leito-cnjim-320",
    "originalName": "113 - Mese Man Nashod - Behzad Leito  Cnjim (320).mp3",
    "path": "uploads/113-mese-man-nashod-behzad-leito-cnjim-320.enc",
    "timestamp": 1777495736989,
    "expire_in_hours": 1,
    "passwordProtected": false
  }
]